setup.py
jiocloud/__init__.py
jiocloud/apply_resources.py
jiocloud/orchestrate.py
jiocloud/utils.py
jiocloud.egg-info/PKG-INFO
jiocloud.egg-info/SOURCES.txt
jiocloud.egg-info/dependency_links.txt
jiocloud.egg-info/requires.txt
jiocloud.egg-info/top_level.txt