Metadata-Version: 1.0
Name: jiocloud
Version: 0.4
Summary: Various Python utilities used for JioCloud
Home-page: http://github.com/JioCloud/python-jiocloud
Author: Soren Hansen
Author-email: Soren.Hansen@ril.com
License: Apache 2.0
Keywords: etcd openstack cloud
Platform: UNKNOWN
